setup.py
GaBidistributions/Binomialdistribution.py
GaBidistributions/Gaussiandistribution.py
GaBidistributions/Generaldistribution.py
GaBidistributions/__init__.py
GaBidistributions.egg-info/PKG-INFO
GaBidistributions.egg-info/SOURCES.txt
GaBidistributions.egg-info/dependency_links.txt
GaBidistributions.egg-info/not-zip-safe
GaBidistributions.egg-info/top_level.txt